mlx/__main__.py
mlx/_reprlib_fix.py
mlx/core.cpython-313-aarch64-linux-gnu.so,Cue_VhC1OlSgxMoehswcruBrGxqhZ88c7KsYFA89oSA,1441400
mlx/extension.py
mlx/py.typed
mlx/utils.py
mlx/_distributed_utils/common.py
mlx/_distributed_utils/config.py
mlx/_distributed_utils/launch.py
mlx/core/__init__.pyi
mlx/core/core/__init__.pyi
mlx/core/core/cuda.pyi
mlx/core/core/distributed.pyi
mlx/core/core/fast.pyi
mlx/core/core/fft.pyi
mlx/core/core/linalg.pyi
mlx/core/core/metal.pyi
mlx/core/core/random.pyi
mlx/nn/__init__.py
mlx/nn/init.py
mlx/nn/losses.py
mlx/nn/utils.py
mlx/nn/layers/__init__.py
mlx/nn/layers/activations.py
mlx/nn/layers/base.py
mlx/nn/layers/containers.py
mlx/nn/layers/convolution.py
mlx/nn/layers/convolution_transpose.py
mlx/nn/layers/distributed.py
mlx/nn/layers/dropout.py
mlx/nn/layers/embedding.py
mlx/nn/layers/linear.py
mlx/nn/layers/normalization.py
mlx/nn/layers/pooling.py
mlx/nn/layers/positional_encoding.py
mlx/nn/layers/quantized.py
mlx/nn/layers/recurrent.py
mlx/nn/layers/transformer.py
mlx/nn/layers/upsample.py
mlx/optimizers/__init__.py
mlx/optimizers/optimizers.py
mlx/optimizers/schedulers.py
mlx-0.30.1.dist-info/METADATA
mlx-0.30.1.dist-info/WHEEL
mlx-0.30.1.dist-info/entry_points.txt
mlx-0.30.1.dist-info/top_level.txt
mlx-0.30.1.dist-info/RECORD
mlx-0.30.1.dist-info/licenses/LICENSE
