Metadata-Version: 2.4
Name: mlx
Version: 0.30.1
Summary: A framework for machine learning on Apple silicon.
Home-page: https://github.com/ml-explore/mlx
Author: MLX Contributors
Author-email: mlx@group.apple.com
License: MIT
Requires-Python: >=3.10
License-File: LICENSE
Requires-Dist: mlx-metal==0.30.1; platform_system == "Darwin"
Provides-Extra: dev
Requires-Dist: nanobind==2.10.2; extra == "dev"
Requires-Dist: numpy; extra == "dev"
Requires-Dist: pre-commit; extra == "dev"
Requires-Dist: setuptools>=80; extra == "dev"
Requires-Dist: torch; extra == "dev"
Requires-Dist: typing_extensions; extra == "dev"
Provides-Extra: cuda
Requires-Dist: mlx-cuda-12==0.30.1; platform_system == "Linux" and extra == "cuda"
Provides-Extra: cuda12
Requires-Dist: mlx-cuda-12==0.30.1; platform_system == "Linux" and extra == "cuda12"
Provides-Extra: cuda13
Requires-Dist: mlx-cuda-13==0.30.1; platform_system == "Linux" and extra == "cuda13"
Provides-Extra: cpu
Requires-Dist: mlx-cpu==0.30.1; platform_system == "Linux" and extra == "cpu"
Dynamic: author
Dynamic: author-email
Dynamic: description
Dynamic: description-content-type
Dynamic: home-page
Dynamic: license
Dynamic: license-file
Dynamic: provides-extra
Dynamic: requires-dist
Dynamic: requires-python
Dynamic: summary
